gensbi_examples/__init__.py
gensbi_examples/c2st.py
gensbi_examples/c2st_v2.py.bk
gensbi_examples/graph.py
gensbi_examples/mask.py
gensbi_examples/sbi_tasks.py.bk
gensbi_examples/tasks.py
gensbi_examples/utils.py
gensbi_examples/utils.py.bk
gensbi_examples-0.0.2.dist-info/METADATA
gensbi_examples-0.0.2.dist-info/WHEEL
gensbi_examples-0.0.2.dist-info/licenses/LICENSE
gensbi_examples-0.0.2.dist-info/RECORD
