Metadata-Version: 2.4
Name: gensbi-examples
Version: 0.0.2
Summary: Examples for the GenSBI library
Project-URL: Homepage, https://github.com/aurelio-amerio/GenSBI-examples
Project-URL: Issues, https://github.com/aurelio-amerio/GenSBI-examples/issues
Author-email: Aurelio Amerio <aure.amerio@gmail.com>
License:    Copyright 2025 Amerio Aurelio
License-File: LICENSE
Requires-Python: >=3.11
Requires-Dist: datasets
Requires-Dist: flax>=0.12.0
Requires-Dist: grain>=0.2.12
Requires-Dist: huggingface-hub
Requires-Dist: jax<=0.8.1,>=0.7.2
Requires-Dist: matplotlib>=3.10
Requires-Dist: numpy>=2.0
Requires-Dist: scikit-learn>=1.7.0
